xpcsutilities/__init__.py
xpcsutilities/xpcsutilities-logo.svg
xpcsutilities/bin/__init__.py
xpcsutilities/bin/id02xpcs_h52ascii.py
xpcsutilities/bin/main.py
xpcsutilities/gui/__init__.py
xpcsutilities/gui/docks.py
xpcsutilities/gui/mainwindow.py
xpcsutilities/gui/contin/__init__.py
xpcsutilities/gui/contin/tab_contin.py
xpcsutilities/gui/contin/tab_res_contin.py
xpcsutilities/gui/export/__init__.py
xpcsutilities/gui/export/dialog.py
xpcsutilities/gui/fit/__init__.py
xpcsutilities/gui/fit/curvefitwidget.py
xpcsutilities/gui/fit/datafilewidget.py
xpcsutilities/gui/fit/fittab.py
xpcsutilities/gui/fit/parametertable.py
xpcsutilities/gui/fit/paramwidget.py
xpcsutilities/gui/fit/resultgraph.py
xpcsutilities/gui/graphs/__init__.py
xpcsutilities/gui/graphs/g2.py
xpcsutilities/gui/graphs/saxs1D.py
xpcsutilities/gui/graphs/saxs2D.py
xpcsutilities/gui/graphs/ttcf.py
xpcsutilities/tools/__init__.py
xpcsutilities/tools/common.py
xpcsutilities/tools/contin.py
xpcsutilities/tools/graphs.py
xpcsutilities/tools/result_file.py
xpcsutilities/tools/result_file_old.py
xpcsutilities-1.0.4.dist-info/METADATA
xpcsutilities-1.0.4.dist-info/WHEEL
xpcsutilities-1.0.4.dist-info/entry_points.txt
xpcsutilities-1.0.4.dist-info/top_level.txt
xpcsutilities-1.0.4.dist-info/RECORD
