Metadata-Version: 2.2
Name: xpcsutilities
Version: 1.0.4
Summary: ESRF ID02 XPCSUtilities
Home-page: https://gitlab.esrf.fr/id02/xpcsutilities
Author: William Chèvremont
Author-email: william.chevremont@esrf.fr
Requires-Python: >3.6
Requires-Dist: numpy
Requires-Dist: scipy
Requires-Dist: h5py>=3.4
Requires-Dist: hdf5plugin
Requires-Dist: fabio
Requires-Dist: watchdog
Requires-Dist: PyQt5
Requires-Dist: matplotlib
Requires-Dist: pandas
Dynamic: author
Dynamic: author-email
Dynamic: description
Dynamic: home-page
Dynamic: requires-dist
Dynamic: requires-python
Dynamic: summary
